knowipy/__init__.py
knowipy/base_client.py
knowipy/client.py
knowipy/decorators.py
knowipy/errors.py
knowipy/utils.py
knowipy/version.py
tests/__init__.py
knowipy-1.1.0.dist-info/LICENSE
knowipy-1.1.0.dist-info/METADATA
knowipy-1.1.0.dist-info/WHEEL
knowipy-1.1.0.dist-info/top_level.txt
knowipy-1.1.0.dist-info/RECORD
