Metadata-Version: 2.1
Name: knowipy
Version: 1.1.0
Summary: The official Python3 Knowi API SDK.
Home-page: https://github.com/ezeagwulae/knowi-python-sdk
Author: Manny Ezeagwula
Author-email: manny@knowi.com
License: MIT
Keywords: knowi single-sign-on management-api api sdk analytics
Platform: UNKNOWN
Requires-Python: >=3.6
Requires-Dist: requests
Requires-Dist: pytz
